PyQt5/Qt5/qsci/api/python/PyQtDataVisualization.api
PyQt5/QtDataVisualization.pyd
PyQt5/QtDataVisualization.pyi
PyQt5/bindings/QtDataVisualization/QtDataVisualization.toml
PyQt5/bindings/QtDataVisualization/QtDataVisualizationmod.sip
PyQt5/bindings/QtDataVisualization/q3dbars.sip
PyQt5/bindings/QtDataVisualization/q3dcamera.sip
PyQt5/bindings/QtDataVisualization/q3dinputhandler.sip
PyQt5/bindings/QtDataVisualization/q3dlight.sip
PyQt5/bindings/QtDataVisualization/q3dobject.sip
PyQt5/bindings/QtDataVisualization/q3dscatter.sip
PyQt5/bindings/QtDataVisualization/q3dscene.sip
PyQt5/bindings/QtDataVisualization/q3dsurface.sip
PyQt5/bindings/QtDataVisualization/q3dtheme.sip
PyQt5/bindings/QtDataVisualization/qabstract3daxis.sip
PyQt5/bindings/QtDataVisualization/qabstract3dgraph.sip
PyQt5/bindings/QtDataVisualization/qabstract3dinputhandler.sip
PyQt5/bindings/QtDataVisualization/qabstract3dseries.sip
PyQt5/bindings/QtDataVisualization/qabstractdataproxy.sip
PyQt5/bindings/QtDataVisualization/qbar3dseries.sip
PyQt5/bindings/QtDataVisualization/qbardataitem.sip
PyQt5/bindings/QtDataVisualization/qbardataproxy.sip
PyQt5/bindings/QtDataVisualization/qcategory3daxis.sip
PyQt5/bindings/QtDataVisualization/qcustom3ditem.sip
PyQt5/bindings/QtDataVisualization/qcustom3dlabel.sip
PyQt5/bindings/QtDataVisualization/qcustom3dvolume.sip
PyQt5/bindings/QtDataVisualization/qdatavisualizationglobal.sip
PyQt5/bindings/QtDataVisualization/qheightmapsurfacedataproxy.sip
PyQt5/bindings/QtDataVisualization/qitemmodelbardataproxy.sip
PyQt5/bindings/QtDataVisualization/qitemmodelscatterdataproxy.sip
PyQt5/bindings/QtDataVisualization/qitemmodelsurfacedataproxy.sip
PyQt5/bindings/QtDataVisualization/qlist.sip
PyQt5/bindings/QtDataVisualization/qlogvalue3daxisformatter.sip
PyQt5/bindings/QtDataVisualization/qscatter3dseries.sip
PyQt5/bindings/QtDataVisualization/qscatterdataitem.sip
PyQt5/bindings/QtDataVisualization/qscatterdataproxy.sip
PyQtDataVisualization-5.15.6.dist-info/WHEEL
PyQtDataVisualization-5.15.6.dist-info/METADATA
PyQtDataVisualization-5.15.6.dist-info/RECORD
